emergentic/__devel__.py
emergentic/__init__.py
emergentic/graph/__init__.py
emergentic/propagant/__init__.py
emergentic-0.1.0.dist-info/WHEEL
emergentic-0.1.0.dist-info/WHEEL.json
emergentic-0.1.0.dist-info/entry_points.txt
emergentic-0.1.0.dist-info/METADATA
emergentic-0.1.0.dist-info/METADATA.json
emergentic-0.1.0.dist-info/RECORD
